pywebfs/__init__.py
pywebfs/pywebfs.py
pywebfs/version.py
pywebfs-1.1.24.dist-info/licenses/LICENSE
pywebfs-1.1.24.dist-info/METADATA
pywebfs-1.1.24.dist-info/WHEEL
pywebfs-1.1.24.dist-info/entry_points.txt
pywebfs-1.1.24.dist-info/top_level.txt
pywebfs-1.1.24.dist-info/RECORD
