Metadata-Version: 2.4
Name: pywebfs
Version: 1.1.24
Summary: Simple Python HTTP File Server
Home-page: https://github.com/joknarf/pywebfs
Author: Franck Jouvanceau
Maintainer: Franck Jouvanceau
License: MIT License
Project-URL: Homepage, https://github.com/joknarf/pywebfs
Project-URL: Documentation, https://github.com/joknarf/pywebfs/blob/main/README.md
Project-URL: Repository, https://github.com/joknarf/pywebfs.git
Keywords: http,fileserver,browser,explorer
Classifier: Development Status :: 5 - Production/Stable
Classifier: Intended Audience :: System Administrators
Classifier: License :: OSI Approved :: MIT License
Classifier: Operating System :: POSIX
Classifier: Operating System :: Unix
Classifier: Operating System :: Microsoft :: Windows
Classifier: Operating System :: MacOS
Classifier: Programming Language :: Python
Classifier: Programming Language :: Python :: 3
Classifier: Programming Language :: Python :: 3.6
Classifier: Programming Language :: Python :: 3.7
Classifier: Programming Language :: Python :: 3.8
Classifier: Programming Language :: Python :: 3.9
Classifier: Programming Language :: Python :: 3.10
Classifier: Programming Language :: Python :: 3.11
Classifier: Topic :: Software Development :: Libraries :: Python Modules
Classifier: Topic :: System :: Clustering
Classifier: Topic :: System :: Networking
Classifier: Topic :: System :: Systems Administration
Requires-Python: >=3.6
License-File: LICENSE
Requires-Dist: cryptography>=40.0.2
Requires-Dist: python-daemon>=2.3.2
Dynamic: license-file
